zac_pyutils
zac_pyutils/ConvertYolo
