Metadata-Version: 1.2
Name: zac-pyutils
Version: 1.70.53
Summary: collection of some useful functions
Home-page: https://github.com/Zachary4biz/ExqUtils
Author: zach
Author-email: 2achx0121@gmail.com
Maintainer: zach
Maintainer-email: 2achx0121@gmail.com
License: BSD License
Platform: all
Classifier: Development Status :: 4 - Beta
Classifier: Operating System :: OS Independent
Classifier: Intended Audience :: Developers
Classifier: License :: OSI Approved :: BSD License
Classifier: Programming Language :: Python
Classifier: Programming Language :: Python :: Implementation
Classifier: Programming Language :: Python :: 2.7
Classifier: Programming Language :: Python :: 3
Classifier: Programming Language :: Python :: 3.4
Classifier: Programming Language :: Python :: 3.5
Classifier: Programming Language :: Python :: 3.6
Classifier: Topic :: Software Development :: Libraries
